flipswitch/__init__.py
flipswitch/provider.py
flipswitch/sse_client.py
flipswitch/types.py
flipswitch_sdk-0.1.2.dist-info/licenses/LICENSE
flipswitch_sdk-0.1.2.dist-info/METADATA
flipswitch_sdk-0.1.2.dist-info/WHEEL
flipswitch_sdk-0.1.2.dist-info/top_level.txt
flipswitch_sdk-0.1.2.dist-info/RECORD
