Metadata-Version: 2.4
Name: flipswitch-sdk
Version: 0.1.2
Summary: Flipswitch SDK with real-time SSE support for OpenFeature
License: MIT
Project-URL: Homepage, https://github.com/flipswitch-io/python-sdk
Project-URL: Documentation, https://flipswitch.io/docs/sdks/python
Project-URL: Repository, https://github.com/flipswitch-io/python-sdk
Keywords: feature-flags,openfeature,flipswitch,sse,real-time
Classifier: Development Status :: 4 - Beta
Classifier: Intended Audience :: Developers
Classifier: License :: OSI Approved :: MIT License
Classifier: Operating System :: OS Independent
Classifier: Programming Language :: Python :: 3
Classifier: Programming Language :: Python :: 3.9
Classifier: Programming Language :: Python :: 3.10
Classifier: Programming Language :: Python :: 3.11
Classifier: Programming Language :: Python :: 3.12
Classifier: Topic :: Software Development :: Libraries :: Python Modules
Requires-Python: >=3.9
License-File: LICENSE
Requires-Dist: openfeature-sdk>=0.7.0
Requires-Dist: openfeature-provider-ofrep>=0.2.0
Requires-Dist: httpx>=0.27.0
Provides-Extra: dev
Requires-Dist: pytest>=8.0.0; extra == "dev"
Requires-Dist: pytest-httpserver>=1.0.0; extra == "dev"
Requires-Dist: pytest-asyncio>=0.23.0; extra == "dev"
Dynamic: license-file
